APT_stats/__init__.py
APT_stats/calc.py
APT_stats/material.py
APT_stats/molecular.py
APT_stats-0.0.4.dist-info/LICENSE
APT_stats-0.0.4.dist-info/METADATA
APT_stats-0.0.4.dist-info/WHEEL
APT_stats-0.0.4.dist-info/top_level.txt
APT_stats-0.0.4.dist-info/RECORD
