Metadata-Version: 2.1
Name: APT-stats
Version: 0.0.4
Summary: Python Tool for APT Mass Statistics
Home-page: https://victorgarric.github.io/APT_stats/
Author: Victor Garric
Author-email: victor.garric@gmail.com
License: GNU GPLv3
Keywords: TEM image analysis precipitate cluster clustering
Platform: UNKNOWN
Requires-Dist: mendeleev
Requires-Dist: tableprint
Requires-Dist: matplotlib
Requires-Dist: numpy
